MANIFEST.in
README.md
README.rst
requirements-develop.txt
requirements.txt
setup.py
brendapy/__init__.py
brendapy/_version.py
brendapy/examples.py
brendapy/parser.py
brendapy/settings.py
brendapy/substances.py
brendapy/taxonomy.py
brendapy/tissues.py
brendapy/utils.py
brendapy.egg-info/PKG-INFO
brendapy.egg-info/SOURCES.txt
brendapy.egg-info/dependency_links.txt
brendapy.egg-info/not-zip-safe
brendapy.egg-info/requires.txt
brendapy.egg-info/top_level.txt
brendapy/ontology/__init__.py
brendapy/ontology/owl.py
brendapy/ontology/pubchem.py
brendapy/resources/README.md
brendapy/tests/__init__.py
brendapy/tests/test_brenda.py
brendapy/tests/test_examples.py
brendapy/tests/test_taxonomy.py