Metadata-Version: 1.1
Name: brendapy
Version: 0.4.1
Summary: Parsing BRENDA information
Home-page: https://github.com/matthiaskoenig/brendapy
Author: Matthias König
Author-email: konigmatt@googlemail.com
License: UNKNOWN
Keywords: BRENDA
Platform: UNKNOWN
Classifier: Development Status :: 4 - Beta
Classifier: Intended Audience :: Science/Research
Classifier: License :: OSI Approved :: GNU Lesser General Public License v3 (LGPLv3)
Classifier: Operating System :: OS Independent
Classifier: Programming Language :: Python :: 3.6
Classifier: Programming Language :: Python :: 3.7
Classifier: Topic :: Scientific/Engineering
Classifier: Topic :: Scientific/Engineering :: Bio-Informatics
